hackertools/__init__.py
hackertools/numbertools.py
hackertools/texttools.py
hackertools-0.0.2.dist-info/METADATA
hackertools-0.0.2.dist-info/WHEEL
hackertools-0.0.2.dist-info/licenses/LICENSE
hackertools-0.0.2.dist-info/RECORD
