Metadata-Version: 2.1
Name: hackertools
Version: 0.0.2
Summary: The essential utilities that every hackathon developer needs
Project-URL: Homepage, https://github.com/pypa/sampleproject
Project-URL: Bug Tracker, https://github.com/pypa/sampleproject/issues
Author-email: Jonathan Lei <jonathan@tensordock.com>
License: Copyright (c) 2022 Jonathan Lei
Classifier: License :: OSI Approved :: MIT License
Classifier: Operating System :: OS Independent
Classifier: Programming Language :: Python :: 3
Requires-Python: >=3.7
